netrun/errors/__init__.py
netrun/errors/auth.py
netrun/errors/authorization.py
netrun/errors/base.py
netrun/errors/handlers.py
netrun/errors/middleware.py
netrun/errors/py.typed
netrun/errors/resource.py
netrun/errors/service.py
netrun_errors/__init__.py
netrun_errors-2.0.0.dist-info/METADATA
netrun_errors-2.0.0.dist-info/WHEEL
netrun_errors-2.0.0.dist-info/licenses/LICENSE
netrun_errors-2.0.0.dist-info/RECORD
