Metadata-Version: 2.4
Name: netrun-errors
Version: 2.0.0
Summary: Unified error handling for Netrun Systems FastAPI applications
Project-URL: Homepage, https://www.netrunsystems.com
Project-URL: Documentation, https://github.com/netrun-systems/netrun-errors
Project-URL: Repository, https://github.com/netrun-systems/netrun-errors
Project-URL: Bug Tracker, https://github.com/netrun-systems/netrun-errors/issues
Author-email: Netrun Systems <dev@netrunsystems.com>
Maintainer-email: Daniel Garza <daniel@netrunsystems.com>
License: MIT
License-File: LICENSE
Keywords: api,correlation-id,error-handling,exception-handling,fastapi,netrun,rest,structured-logging
Classifier: Development Status :: 5 - Production/Stable
Classifier: Framework :: FastAPI
Classifier: Intended Audience :: Developers
Classifier: License :: OSI Approved :: MIT License
Classifier: Operating System :: OS Independent
Classifier: Programming Language :: Python :: 3
Classifier: Programming Language :: Python :: 3.11
Classifier: Programming Language :: Python :: 3.12
Classifier: Topic :: Internet :: WWW/HTTP
Classifier: Topic :: Software Development :: Libraries :: Python Modules
Classifier: Typing :: Typed
Requires-Python: >=3.11
Requires-Dist: fastapi>=0.115.0
Requires-Dist: netrun-core>=1.0.0
Requires-Dist: starlette>=0.41.0
Provides-Extra: dev
Requires-Dist: black>=24.8.0; extra == 'dev'
Requires-Dist: httpx>=0.27.0; extra == 'dev'
Requires-Dist: mypy>=1.13.0; extra == 'dev'
Requires-Dist: netrun-logging>=2.0.0; extra == 'dev'
Requires-Dist: pytest-asyncio>=0.24.0; extra == 'dev'
Requires-Dist: pytest-cov>=6.0.0; extra == 'dev'
Requires-Dist: pytest>=8.3.0; extra == 'dev'
Requires-Dist: ruff>=0.7.0; extra == 'dev'
Provides-Extra: logging
Requires-Dist: netrun-logging>=2.0.0; extra == 'logging'
